MANIFEST.in
README.rst
setup.py
fempdesolver/__init__.py
fempdesolver/solver1d.py
fempdesolver/solver2d.py
fempdesolver.egg-info/PKG-INFO
fempdesolver.egg-info/SOURCES.txt
fempdesolver.egg-info/dependency_links.txt
fempdesolver.egg-info/top_level.txt
fempdesolver/mesh/__init__.py
fempdesolver/mesh/mesh.py
fempdesolver/mesh/mesh_1d.py
fempdesolver/mesh/mesh_2d.py