Metadata-Version: 1.1
Name: fempdesolver
Version: 1.1
Summary: Solve 1D and 2D PDE by finite elements method.
Home-page: UNKNOWN
Author: Andrei Chertkov
Author-email: andrey.mipt@mail.ru
License: MIT License
Keywords: finite element,pde,pde solver
Platform: UNKNOWN
Classifier: Environment :: Web Environment
Classifier: Intended Audience :: Developers
Classifier: Programming Language :: Python
Requires: python (>= 2.5)
